perform.py
perform-0.0.8.dist-info/WHEEL
perform-0.0.8.dist-info/top_level.txt
perform-0.0.8.dist-info/metadata.json
perform-0.0.8.dist-info/METADATA
perform-0.0.8.dist-info/DESCRIPTION.rst
perform-0.0.8.dist-info/RECORD
