Metadata-Version: 2.0
Name: perform
Version: 0.0.8
Summary: Easily call processes from python
Home-page: http://github.com/BenDoan/perform
Author: Ben Doan
Author-email: ben@bendoan.me
License: MIT
Platform: UNKNOWN
Classifier: Programming Language :: Python :: 2
Classifier: Programming Language :: Python :: 2.6
Classifier: Programming Language :: Python :: 2.7
Classifier: Programming Language :: Python :: 3
Classifier: Intended Audience :: Developers
Classifier: License :: OSI Approved :: MIT License
Classifier: Topic :: Software Development :: Libraries
Classifier: Topic :: Utilities
